{
    "id": 2870,
    "name": "g",
    "author": "Dact",
    "creators": ["Dact"],
    "verifier": "Dact",
    "verification": "#",
    "percentToQualify": "100",
    "records": [
        {
            "user": "yeeee",
            "link": "#",
            "percent": 100,
            "mobile": false
        },
        {
            "user": "MacacoChucrut",
            "link": "#",
            "percent": 100,
            "mobile": false
        },
        {
            "user": "Herobrain",
            "link": "#",
            "percent": 100,
            "mobile": false
        },
        {
            "user": "lolpanda",
            "link": "https://youtu.be/yHu45UxebyQ",
            "percent": 100,
            "mobile": false
        }
    ],
    "tags": ["Wave"]
}
